chippapi/__init__.py
chippapi/api.py
chippapi-1.0.3.dist-info/LICENSE
chippapi-1.0.3.dist-info/METADATA
chippapi-1.0.3.dist-info/WHEEL
chippapi-1.0.3.dist-info/top_level.txt
chippapi-1.0.3.dist-info/RECORD
