Metadata-Version: 2.1
Name: chippapi
Version: 1.0.3
Summary: This is a simple python wrapper for [Chipp](https://chipp.ai/).
Home-page: https://github.com/skilledkitten/chippapi
Author: skilledkitten
Author-email: me@skilledkitten.dev
Classifier: Development Status :: 5 - Production/Stable
Classifier: Intended Audience :: Developers
Classifier: License :: OSI Approved :: MIT License
Classifier: Programming Language :: Python :: 3
Requires-Python: >=3.6
License-File: LICENSE
Requires-Dist: requests >=2.25.1
